gtrpy/__init__.py
gtrpy/run.py
gtrpy/equations/grtensorsEP.py
gtrpy/equations/scalarfieldEP.py
gtrpy/equations/tensorfieldEP.py
gtrpy/equations/vectorfieldEP.py
gtrpy/res/images3D/LX0.png
gtrpy/res/images3D/LX1.png
gtrpy/res/images3D/LX2.png
gtrpy/res/images3D/LX_scalarfield.png
gtrpy/res/images3D/LX_tensorfield_02.png
gtrpy/res/images3D/LX_tensorfield_11.png
gtrpy/res/images3D/LX_tensorfield_20.png
gtrpy/res/images3D/LX_vectorfield_01.png
gtrpy/res/images3D/LX_vectorfield_10.png
gtrpy/res/images3D/chrissymbol.png
gtrpy/res/images3D/cov_scalarfield.png
gtrpy/res/images3D/cov_tensorfield_02.png
gtrpy/res/images3D/cov_tensorfield_11.png
gtrpy/res/images3D/cov_tensorfield_20.png
gtrpy/res/images3D/cov_vectorfield_01.png
gtrpy/res/images3D/cov_vectorfield_10.png
gtrpy/res/images3D/e.png
gtrpy/res/images3D/einsteintensor.png
gtrpy/res/images3D/g0b.png
gtrpy/res/images3D/g1b.png
gtrpy/res/images3D/g2b.png
gtrpy/res/images3D/inversemetrictensor.png
gtrpy/res/images3D/kretschmannscalar.png
gtrpy/res/images3D/metrictensor.png
gtrpy/res/images3D/ricciscalar.png
gtrpy/res/images3D/riccitensor.png
gtrpy/res/images3D/riemanntensor.png
gtrpy/res/images3D/scalarfield.png
gtrpy/res/images3D/tensorfield_02.png
gtrpy/res/images3D/tensorfield_02_0.png
gtrpy/res/images3D/tensorfield_02_1.png
gtrpy/res/images3D/tensorfield_02_2.png
gtrpy/res/images3D/tensorfield_11.png
gtrpy/res/images3D/tensorfield_11_0.png
gtrpy/res/images3D/tensorfield_11_1.png
gtrpy/res/images3D/tensorfield_11_2.png
gtrpy/res/images3D/tensorfield_20.png
gtrpy/res/images3D/tensorfield_20_0.png
gtrpy/res/images3D/tensorfield_20_1.png
gtrpy/res/images3D/tensorfield_20_2.png
gtrpy/res/images3D/tracelessriccitensor.png
gtrpy/res/images3D/vectorfield_01.png
gtrpy/res/images3D/vectorfield_01_0.png
gtrpy/res/images3D/vectorfield_01_1.png
gtrpy/res/images3D/vectorfield_01_2.png
gtrpy/res/images3D/vectorfield_10.png
gtrpy/res/images3D/vectorfield_10_0.png
gtrpy/res/images3D/vectorfield_10_1.png
gtrpy-1.9.dist-info/METADATA
gtrpy-1.9.dist-info/WHEEL
gtrpy-1.9.dist-info/licenses/LICENSE
gtrpy-1.9.dist-info/RECORD
