Metadata-Version: 2.1
Name: gtrpy
Version: 1.9
Summary: GTRPy is a python package that allows you to calculate the well-known tensors in the General Theory of Relativity without writing a single line of code. Furthermore, you can apply many operations to 6 different types of fields, in both 3D and 4D.
Project-URL: Homepage, https://github.com/camarman/GTRPy
Project-URL: Bug Tracker, https://github.com/camarman/GTRPy/issues
Author: Arman Çam
License-File: LICENSE
Classifier: Development Status :: 5 - Production/Stable
Classifier: Intended Audience :: Science/Research
Classifier: License :: OSI Approved :: MIT License
Classifier: Operating System :: MacOS
Classifier: Operating System :: POSIX :: Linux
Classifier: Programming Language :: Python :: 3
Classifier: Topic :: Scientific/Engineering :: Physics
Requires-Python: >=3.7
